devinstaller_core/__init__.py
devinstaller_core/block_interface.py
devinstaller_core/block_platform.py
devinstaller_core/command.py
devinstaller_core/command_python.py
devinstaller_core/command_shell.py
devinstaller_core/common_models.py
devinstaller_core/constants.py
devinstaller_core/dependency_graph.py
devinstaller_core/exception.py
devinstaller_core/extension.py
devinstaller_core/file_manager.py
devinstaller_core/lib.py
devinstaller_core/messages.py
devinstaller_core/module_app.py
devinstaller_core/module_base.py
devinstaller_core/module_file.py
devinstaller_core/module_folder.py
devinstaller_core/module_group.py
devinstaller_core/module_link.py
devinstaller_core/module_phony.py
devinstaller_core/py.typed
devinstaller_core/schema.py
devinstaller_core/settings.py
devinstaller_core/user_interaction.py
devinstaller_core/utilities.py
devinstaller_core-0.9.1.dist-info/LICENSE.org
devinstaller_core-0.9.1.dist-info/WHEEL
devinstaller_core-0.9.1.dist-info/METADATA
devinstaller_core-0.9.1.dist-info/RECORD
