Metadata-Version: 2.1
Name: devinstaller-core
Version: 0.9.1
Summary: The core library for creating a Devinstaller application.
Home-page: https://justine.kizhak.com/projects/devinstaller-core-py
License: MIT
Author: Justine Kizhakkinedath
Author-email: justine@kizhak.com
Requires-Python: >=3.8,<4.0
Classifier: Development Status :: 3 - Alpha
Classifier: License :: OSI Approved :: MIT License
Classifier: Operating System :: OS Independent
Classifier: Programming Language :: Python :: 3
Classifier: Programming Language :: Python :: 3.8
Classifier: Programming Language :: Python :: 3.9
Requires-Dist: anymarkup (>=0.8.1,<0.9.0)
Requires-Dist: cerberus (>=1.3.2,<2.0.0)
Requires-Dist: oschmod (>=0.3.12,<0.4.0)
Requires-Dist: pydantic (>=1.6.1,<2.0.0)
Requires-Dist: questionary (>=1.5.2,<2.0.0)
Requires-Dist: requests (>=2.24.0,<3.0.0)
Requires-Dist: rich (>=9.2.0,<10.0.0)
Requires-Dist: typeguard (>=2.9.1,<3.0.0)
Project-URL: Bug Reports, https://gitlab.com/justinekizhak/devinstaller/issues
Project-URL: Documentation, https://devinstaller-core.readthedocs.io/en/latest/
Project-URL: Repository, https://gitlab.com/justinekizhak/devinstaller-core-py
Project-URL: Say Thanks!, https://saythanks.io/to/justine%40kizhak.com
